av_helper/__init__.py
av_helper/convert_video_to_audio.py
av_helper/merge_audio_video.py
av_helper/save_audio_video_file.py
av_helper-1.1.0.dist-info/LICENSE
av_helper-1.1.0.dist-info/METADATA
av_helper-1.1.0.dist-info/WHEEL
av_helper-1.1.0.dist-info/top_level.txt
av_helper-1.1.0.dist-info/RECORD
